{
  "experiment_name": "r098_campaign_mem_abstain_ait_ads_public_seed7",
  "dataset_dir": "data/ait_ads_public",
  "model": {
    "type": "campaign_mem_abstain",
    "forecast_encoder": "dlinear",
    "retrieval_encoder": "transformer",
    "hidden_dim": 128,
    "embedding_dim": 128,
    "top_k": 5,
    "similarity_temperature": 0.15,
    "delta_scale": 0.18,
    "use_auxiliary": true,
    "use_contrastive": true,
    "use_hard_negatives": true,
    "use_utility": false
  },
  "history": [
    {
      "epoch": 1,
      "train_loss": 0.8372919148083174,
      "dev_metrics": {
        "AUPRC": 0.2391663389550075,
        "AUROC": 0.6869631621760712,
        "Brier": 0.07006432814232816,
        "LogLoss": 0.27132735822904785,
        "ECE@10": 0.0392458862025211,
        "BestF1": 0.3508771929824562,
        "LeadTime@P80": 11.666666984558105,
        "Precision@P80": 1.0,
        "Recall@P80": 0.013043478260869565,
        "LeadTimeDetail": {
          "threshold": 0.9591109752655029,
          "precision": 1.0,
          "recall": 0.013043478260869565,
          "lead_time": 11.666666984558105
        },
        "Analog-Fidelity@5": 94.86837486837487,
        "TTE-Err@1": 1744.1304931640625
      }
    },
    {
      "epoch": 2,
      "train_loss": 0.45271734259789786,
      "dev_metrics": {
        "AUPRC": 0.2738911825327538,
        "AUROC": 0.7874628550558627,
        "Brier": 0.06545923749689819,
        "LogLoss": 0.23276030775445405,
        "ECE@10": 0.01645956191137203,
        "BestF1": 0.372960372960373,
        "LeadTime@P80": 25.0,
        "Precision@P80": 1.0,
        "Recall@P80": 0.013043478260869565,
        "LeadTimeDetail": {
          "threshold": 0.753591001033783,
          "precision": 1.0,
          "recall": 0.013043478260869565,
          "lead_time": 25.0
        },
        "Analog-Fidelity@5": 94.81923481923482,
        "TTE-Err@1": 234.80435180664062
      }
    },
    {
      "epoch": 3,
      "train_loss": 0.3991926957515395,
      "dev_metrics": {
        "AUPRC": 0.272748551516802,
        "AUROC": 0.7909009412819363,
        "Brier": 0.06453530633664621,
        "LogLoss": 0.2306787162978908,
        "ECE@10": 0.01734964101783792,
        "BestF1": 0.3849765258215962,
        "LeadTime@P80": 30.0,
        "Precision@P80": 1.0,
        "Recall@P80": 0.004347826086956522,
        "LeadTimeDetail": {
          "threshold": 0.8672090172767639,
          "precision": 1.0,
          "recall": 0.004347826086956522,
          "lead_time": 30.0
        },
        "Analog-Fidelity@5": 95.17023517023517,
        "TTE-Err@1": 1734.2825927734375
      }
    },
    {
      "epoch": 4,
      "train_loss": 0.3893995715058259,
      "dev_metrics": {
        "AUPRC": 0.255619109450903,
        "AUROC": 0.7871524146288825,
        "Brier": 0.06575050189576981,
        "LogLoss": 0.23315022871175953,
        "ECE@10": 0.018025046290055687,
        "BestF1": 0.3866348448687351,
        "LeadTime@P80": 0.0,
        "Precision@P80": 0.0,
        "Recall@P80": 0.0,
        "LeadTimeDetail": {
          "threshold": 0.0,
          "precision": 0.0,
          "recall": 0.0,
          "lead_time": 0.0
        },
        "Analog-Fidelity@5": 94.94559494559495,
        "TTE-Err@1": 179.93478393554688
      }
    },
    {
      "epoch": 5,
      "train_loss": 0.3740093355992473,
      "dev_metrics": {
        "AUPRC": 0.2685029967683173,
        "AUROC": 0.7913026877168517,
        "Brier": 0.06446100828091793,
        "LogLoss": 0.23170989131612385,
        "ECE@10": 0.017087116276530045,
        "BestF1": 0.3805104408352668,
        "LeadTime@P80": 0.0,
        "Precision@P80": 0.0,
        "Recall@P80": 0.0,
        "LeadTimeDetail": {
          "threshold": 0.0,
          "precision": 0.0,
          "recall": 0.0,
          "lead_time": 0.0
        },
        "Analog-Fidelity@5": 95.47209547209548,
        "TTE-Err@1": 1719.891357421875
      }
    },
    {
      "epoch": 6,
      "train_loss": 0.3662542505854642,
      "dev_metrics": {
        "AUPRC": 0.25758725194829973,
        "AUROC": 0.7849029666152032,
        "Brier": 0.06545326846520882,
        "LogLoss": 0.23513616776847104,
        "ECE@10": 0.01695858005217462,
        "BestF1": 0.36658932714617165,
        "LeadTime@P80": 0.0,
        "Precision@P80": 0.0,
        "Recall@P80": 0.0,
        "LeadTimeDetail": {
          "threshold": 0.0,
          "precision": 0.0,
          "recall": 0.0,
          "lead_time": 0.0
        },
        "Analog-Fidelity@5": 95.38083538083538,
        "TTE-Err@1": 1777.45654296875
      }
    },
    {
      "epoch": 7,
      "train_loss": 0.36828927845923,
      "dev_metrics": {
        "AUPRC": 0.2683501934177831,
        "AUROC": 0.7878828626923652,
        "Brier": 0.06504719009374225,
        "LogLoss": 0.2339589338434943,
        "ECE@10": 0.021241383638314505,
        "BestF1": 0.3687943262411348,
        "LeadTime@P80": 0.0,
        "Precision@P80": 0.0,
        "Recall@P80": 0.0,
        "LeadTimeDetail": {
          "threshold": 0.0,
          "precision": 0.0,
          "recall": 0.0,
          "lead_time": 0.0
        },
        "Analog-Fidelity@5": 94.93857493857493,
        "TTE-Err@1": 182.28260803222656
      }
    },
    {
      "epoch": 8,
      "train_loss": 0.36785430974023803,
      "dev_metrics": {
        "AUPRC": 0.2595197981083035,
        "AUROC": 0.7879393064063616,
        "Brier": 0.0647035554739845,
        "LogLoss": 0.2344771898050231,
        "ECE@10": 0.017802257990083652,
        "BestF1": 0.375609756097561,
        "LeadTime@P80": 0.0,
        "Precision@P80": 0.0,
        "Recall@P80": 0.0,
        "LeadTimeDetail": {
          "threshold": 0.0,
          "precision": 0.0,
          "recall": 0.0,
          "lead_time": 0.0
        },
        "Analog-Fidelity@5": 95.28255528255528,
        "TTE-Err@1": 1731.978271484375
      }
    },
    {
      "epoch": 9,
      "train_loss": 0.36274503947386083,
      "dev_metrics": {
        "AUPRC": 0.266528762706186,
        "AUROC": 0.7876919501303186,
        "Brier": 0.06410570944793695,
        "LogLoss": 0.2323818842935793,
        "ECE@10": 0.011327863089912224,
        "BestF1": 0.3761904761904762,
        "LeadTime@P80": 0.0,
        "Precision@P80": 0.0,
        "Recall@P80": 0.0,
        "LeadTimeDetail": {
          "threshold": 0.0,
          "precision": 0.0,
          "recall": 0.0,
          "lead_time": 0.0
        },
        "Analog-Fidelity@5": 95.31765531765531,
        "TTE-Err@1": 1721.8695068359375
      }
    },
    {
      "epoch": 10,
      "train_loss": 0.3574744296846506,
      "dev_metrics": {
        "AUPRC": 0.27262578146804833,
        "AUROC": 0.78482826169962,
        "Brier": 0.06478836909831479,
        "LogLoss": 0.2346268162353529,
        "ECE@10": 0.015939314679362642,
        "BestF1": 0.3701923076923077,
        "LeadTime@P80": 0.0,
        "Precision@P80": 0.0,
        "Recall@P80": 0.0,
        "LeadTimeDetail": {
          "threshold": 0.0,
          "precision": 0.0,
          "recall": 0.0,
          "lead_time": 0.0
        },
        "Analog-Fidelity@5": 95.14215514215513,
        "TTE-Err@1": 1751.108642578125
      }
    },
    {
      "epoch": 11,
      "train_loss": 0.35955259917676285,
      "dev_metrics": {
        "AUPRC": 0.27519967545214835,
        "AUROC": 0.7882621976526055,
        "Brier": 0.06498020848265663,
        "LogLoss": 0.23534904090061473,
        "ECE@10": 0.018515093728470742,
        "BestF1": 0.37529691211401417,
        "LeadTime@P80": 5.0,
        "Precision@P80": 1.0,
        "Recall@P80": 0.004347826086956522,
        "LeadTimeDetail": {
          "threshold": 0.7986670136451721,
          "precision": 1.0,
          "recall": 0.004347826086956522,
          "lead_time": 5.0
        },
        "Analog-Fidelity@5": 95.35275535275535,
        "TTE-Err@1": 1704.1522216796875
      }
    },
    {
      "epoch": 12,
      "train_loss": 0.35582795151886104,
      "dev_metrics": {
        "AUPRC": 0.26411953758012297,
        "AUROC": 0.7873483075186347,
        "Brier": 0.06504862875557284,
        "LogLoss": 0.2350026841536127,
        "ECE@10": 0.012416372509690727,
        "BestF1": 0.38207547169811323,
        "LeadTime@P80": 17.5,
        "Precision@P80": 1.0,
        "Recall@P80": 0.008695652173913044,
        "LeadTimeDetail": {
          "threshold": 0.7473419904708862,
          "precision": 1.0,
          "recall": 0.008695652173913044,
          "lead_time": 17.5
        },
        "Analog-Fidelity@5": 94.94559494559495,
        "TTE-Err@1": 163.1086883544922
      }
    },
    {
      "epoch": 13,
      "train_loss": 0.3654669410749177,
      "dev_metrics": {
        "AUPRC": 0.24828522879219567,
        "AUROC": 0.7798479339940567,
        "Brier": 0.06583486264546673,
        "LogLoss": 0.24003556731765535,
        "ECE@10": 0.018815959735684264,
        "BestF1": 0.3693045563549161,
        "LeadTime@P80": 0.0,
        "Precision@P80": 0.0,
        "Recall@P80": 0.0,
        "LeadTimeDetail": {
          "threshold": 0.0,
          "precision": 0.0,
          "recall": 0.0,
          "lead_time": 0.0
        },
        "Analog-Fidelity@5": 95.31765531765531,
        "TTE-Err@1": 1741.7608642578125
      }
    },
    {
      "epoch": 14,
      "train_loss": 0.3598698725569914,
      "dev_metrics": {
        "AUPRC": 0.271354467490141,
        "AUROC": 0.7764463701711571,
        "Brier": 0.06520029238087294,
        "LogLoss": 0.2408754916702664,
        "ECE@10": 0.016589509726290093,
        "BestF1": 0.36180904522613067,
        "LeadTime@P80": 5.0,
        "Precision@P80": 1.0,
        "Recall@P80": 0.004347826086956522,
        "LeadTimeDetail": {
          "threshold": 0.8195899724960327,
          "precision": 1.0,
          "recall": 0.004347826086956522,
          "lead_time": 5.0
        },
        "Analog-Fidelity@5": 95.37381537381538,
        "TTE-Err@1": 1758.3260498046875
      }
    },
    {
      "epoch": 15,
      "train_loss": 0.3460958464023562,
      "dev_metrics": {
        "AUPRC": 0.28552388794401934,
        "AUROC": 0.7763251821969885,
        "Brier": 0.06502779433864732,
        "LogLoss": 0.2426728840048945,
        "ECE@10": 0.016820015762278404,
        "BestF1": 0.3653846153846154,
        "LeadTime@P80": 12.75,
        "Precision@P80": 0.8,
        "Recall@P80": 0.08695652173913043,
        "LeadTimeDetail": {
          "threshold": 0.7837100028991699,
          "precision": 0.8,
          "recall": 0.08695652173913043,
          "lead_time": 12.75
        },
        "Analog-Fidelity@5": 95.12811512811513,
        "TTE-Err@1": 1823.0
      }
    },
    {
      "epoch": 16,
      "train_loss": 0.3428440895346202,
      "dev_metrics": {
        "AUPRC": 0.275241757462399,
        "AUROC": 0.7758902335773694,
        "Brier": 0.0647223068027428,
        "LogLoss": 0.2416180370888786,
        "ECE@10": 0.018165247592890014,
        "BestF1": 0.3618581907090464,
        "LeadTime@P80": 5.0,
        "Precision@P80": 1.0,
        "Recall@P80": 0.004347826086956522,
        "LeadTimeDetail": {
          "threshold": 0.8435500264167786,
          "precision": 1.0,
          "recall": 0.004347826086956522,
          "lead_time": 5.0
        },
        "Analog-Fidelity@5": 95.07195507195507,
        "TTE-Err@1": 1719.391357421875
      }
    },
    {
      "epoch": 17,
      "train_loss": 0.33983643332886215,
      "dev_metrics": {
        "AUPRC": 0.28526214312741366,
        "AUROC": 0.7769344422863024,
        "Brier": 0.0642424488254054,
        "LogLoss": 0.2406201265146686,
        "ECE@10": 0.014242620651823332,
        "BestF1": 0.365,
        "LeadTime@P80": 5.0,
        "Precision@P80": 1.0,
        "Recall@P80": 0.004347826086956522,
        "LeadTimeDetail": {
          "threshold": 0.8357049822807312,
          "precision": 1.0,
          "recall": 0.004347826086956522,
          "lead_time": 5.0
        },
        "Analog-Fidelity@5": 95.21937521937522,
        "TTE-Err@1": 1779.478271484375
      }
    },
    {
      "epoch": 18,
      "train_loss": 0.33521645052650806,
      "dev_metrics": {
        "AUPRC": 0.2888265349303925,
        "AUROC": 0.7771668575792288,
        "Brier": 0.064321188584365,
        "LogLoss": 0.24106328013563133,
        "ECE@10": 0.012479234062034167,
        "BestF1": 0.3613861386138614,
        "LeadTime@P80": 13.333333015441895,
        "Precision@P80": 0.8571428571428571,
        "Recall@P80": 0.05217391304347826,
        "LeadTimeDetail": {
          "threshold": 0.7446060180664062,
          "precision": 0.8571428571428571,
          "recall": 0.05217391304347826,
          "lead_time": 13.333333015441895
        },
        "Analog-Fidelity@5": 95.26851526851526,
        "TTE-Err@1": 1761.6739501953125
      }
    }
  ],
  "best_dev_score": 1.2415116876155452,
  "dev": {
    "AUPRC": 0.2888265349303925,
    "AUROC": 0.7771668575792288,
    "Brier": 0.064321188584365,
    "LogLoss": 0.24106328013563133,
    "ECE@10": 0.012479234062034167,
    "BestF1": 0.3613861386138614,
    "LeadTime@P80": 13.333333015441895,
    "Precision@P80": 0.8571428571428571,
    "Recall@P80": 0.05217391304347826,
    "LeadTimeDetail": {
      "threshold": 0.7446060180664062,
      "precision": 0.8571428571428571,
      "recall": 0.05217391304347826,
      "lead_time": 13.333333015441895
    },
    "Analog-Fidelity@5": 95.26851526851526,
    "TTE-Err@1": 1761.6739501953125
  },
  "test": {
    "AUPRC": 0.531397753269051,
    "AUROC": 0.8761598706836242,
    "Brier": 0.03337500844734981,
    "LogLoss": 0.13833402173222023,
    "ECE@10": 0.01210685900117991,
    "BestF1": 0.6126914660831508,
    "LeadTime@P80": 15.17241382598877,
    "Precision@P80": 0.8365384615384616,
    "Recall@P80": 0.3466135458167331,
    "LeadTimeDetail": {
      "threshold": 0.5763949751853943,
      "precision": 0.8365384615384616,
      "recall": 0.3466135458167331,
      "lead_time": 15.17241382598877
    },
    "Analog-Fidelity@5": 95.61913081458833,
    "TTE-Err@1": 894.5219116210938
  },
  "test_event_disjoint": {
    "AUPRC": 0.4278383590028006,
    "AUROC": 0.8541432762541842,
    "Brier": 0.06791577977789072,
    "LogLoss": 0.23666013870594604,
    "ECE@10": 0.022536967659076024,
    "BestF1": 0.5297202797202798,
    "LeadTime@P80": 16.052631378173828,
    "Precision@P80": 0.8028169014084507,
    "Recall@P80": 0.0945273631840796,
    "LeadTimeDetail": {
      "threshold": 0.7407670021057129,
      "precision": 0.8028169014084507,
      "recall": 0.0945273631840796,
      "lead_time": 16.052631378173828
    },
    "Analog-Fidelity@5": 95.44560735807168,
    "TTE-Err@1": 1441.3349609375
  }
}