{
  "experiment_name": "r016_campaign_mem_no_hard_negatives_atlasv2_public_event_disjoint_seed13",
  "dataset_dir": "data/atlasv2_public",
  "model": {
    "type": "campaign_mem",
    "encoder": "transformer",
    "hidden_dim": 128,
    "embedding_dim": 128,
    "top_k": 5,
    "use_auxiliary": true,
    "use_contrastive": true,
    "use_hard_negatives": false,
    "use_utility": false
  },
  "history": [
    {
      "epoch": 1,
      "train_loss": 0.29121324243066515,
      "dev_metrics": {
        "AUPRC": 0.4303571428571429,
        "Brier": 0.023393023008461966,
        "LeadTime@P80": 0.0,
        "LeadTimeDetail": {
          "threshold": 0.0,
          "precision": 0.0,
          "recall": 0.0,
          "lead_time": 0.0
        },
        "Analog-Fidelity@5": 72.12903225806451,
        "TTE-Err@1": 25.0
      }
    },
    {
      "epoch": 2,
      "train_loss": 0.2511162368674256,
      "dev_metrics": {
        "AUPRC": 0.03716108162652719,
        "Brier": 0.025233472171282443,
        "LeadTime@P80": 0.0,
        "LeadTimeDetail": {
          "threshold": 0.0,
          "precision": 0.0,
          "recall": 0.0,
          "lead_time": 0.0
        },
        "Analog-Fidelity@5": 78.96774193548387,
        "TTE-Err@1": 25.0
      }
    },
    {
      "epoch": 3,
      "train_loss": 0.2584578487426723,
      "dev_metrics": {
        "AUPRC": 0.03212073517980691,
        "Brier": 0.027156181439596135,
        "LeadTime@P80": 0.0,
        "LeadTimeDetail": {
          "threshold": 0.0,
          "precision": 0.0,
          "recall": 0.0,
          "lead_time": 0.0
        },
        "Analog-Fidelity@5": 78.70967741935485,
        "TTE-Err@1": 31.25
      }
    },
    {
      "epoch": 4,
      "train_loss": 0.23500649113905484,
      "dev_metrics": {
        "AUPRC": 0.6428571428571428,
        "Brier": 0.018571832161952254,
        "LeadTime@P80": 0.0,
        "LeadTimeDetail": {
          "threshold": 0.0,
          "precision": 0.0,
          "recall": 0.0,
          "lead_time": 0.0
        },
        "Analog-Fidelity@5": 77.29032258064517,
        "TTE-Err@1": 31.25
      }
    },
    {
      "epoch": 5,
      "train_loss": 0.2526852419795511,
      "dev_metrics": {
        "AUPRC": 0.4928571428571429,
        "Brier": 0.018072047183143366,
        "LeadTime@P80": 0.0,
        "LeadTimeDetail": {
          "threshold": 0.0,
          "precision": 0.0,
          "recall": 0.0,
          "lead_time": 0.0
        },
        "Analog-Fidelity@5": 81.54838709677419,
        "TTE-Err@1": 31.25
      }
    },
    {
      "epoch": 6,
      "train_loss": 0.2490701694466752,
      "dev_metrics": {
        "AUPRC": 0.5,
        "Brier": 0.018289978681121373,
        "LeadTime@P80": 0.0,
        "LeadTimeDetail": {
          "threshold": 0.0,
          "precision": 0.0,
          "recall": 0.0,
          "lead_time": 0.0
        },
        "Analog-Fidelity@5": 79.09677419354838,
        "TTE-Err@1": 31.25
      }
    },
    {
      "epoch": 7,
      "train_loss": 0.23968950172537537,
      "dev_metrics": {
        "AUPRC": 0.47619047619047616,
        "Brier": 0.0231582880765756,
        "LeadTime@P80": 0.0,
        "LeadTimeDetail": {
          "threshold": 0.0,
          "precision": 0.0,
          "recall": 0.0,
          "lead_time": 0.0
        },
        "Analog-Fidelity@5": 77.29032258064517,
        "TTE-Err@1": 31.25
      }
    },
    {
      "epoch": 8,
      "train_loss": 0.23015235793100644,
      "dev_metrics": {
        "AUPRC": 0.34552845528455284,
        "Brier": 0.02351609644748466,
        "LeadTime@P80": 0.0,
        "LeadTimeDetail": {
          "threshold": 0.0,
          "precision": 0.0,
          "recall": 0.0,
          "lead_time": 0.0
        },
        "Analog-Fidelity@5": 80.64516129032258,
        "TTE-Err@1": 31.25
      }
    },
    {
      "epoch": 9,
      "train_loss": 0.2793687837853279,
      "dev_metrics": {
        "AUPRC": 0.475,
        "Brier": 0.019530019212556343,
        "LeadTime@P80": 0.0,
        "LeadTimeDetail": {
          "threshold": 0.0,
          "precision": 0.0,
          "recall": 0.0,
          "lead_time": 0.0
        },
        "Analog-Fidelity@5": 79.35483870967742,
        "TTE-Err@1": 31.25
      }
    },
    {
      "epoch": 10,
      "train_loss": 0.2318748880058663,
      "dev_metrics": {
        "AUPRC": 0.23581761006289306,
        "Brier": 0.024423894414578918,
        "LeadTime@P80": 0.0,
        "LeadTimeDetail": {
          "threshold": 0.0,
          "precision": 0.0,
          "recall": 0.0,
          "lead_time": 0.0
        },
        "Analog-Fidelity@5": 73.16129032258064,
        "TTE-Err@1": 31.25
      }
    },
    {
      "epoch": 11,
      "train_loss": 0.23362524208685034,
      "dev_metrics": {
        "AUPRC": 0.5595238095238095,
        "Brier": 0.018589772849917474,
        "LeadTime@P80": 10.0,
        "LeadTimeDetail": {
          "threshold": 0.4986630082130432,
          "precision": 1.0,
          "recall": 0.25,
          "lead_time": 10.0
        },
        "Analog-Fidelity@5": 79.87096774193549,
        "TTE-Err@1": 31.25
      }
    },
    {
      "epoch": 12,
      "train_loss": 0.2203270610609011,
      "dev_metrics": {
        "AUPRC": 0.40788770053475937,
        "Brier": 0.022917995414448056,
        "LeadTime@P80": 10.0,
        "LeadTimeDetail": {
          "threshold": 0.19365499913692474,
          "precision": 1.0,
          "recall": 0.25,
          "lead_time": 10.0
        },
        "Analog-Fidelity@5": 77.03225806451613,
        "TTE-Err@1": 31.25
      }
    }
  ],
  "best_dev_score": 1.4157603686635944,
  "dev": {
    "AUPRC": 0.6428571428571428,
    "Brier": 0.018571832161952254,
    "LeadTime@P80": 0.0,
    "LeadTimeDetail": {
      "threshold": 0.0,
      "precision": 0.0,
      "recall": 0.0,
      "lead_time": 0.0
    },
    "Analog-Fidelity@5": 77.29032258064517,
    "TTE-Err@1": 31.25
  },
  "test": {
    "AUPRC": 0.7916666666666666,
    "Brier": 0.04607144647389926,
    "LeadTime@P80": 11.666666984558105,
    "LeadTimeDetail": {
      "threshold": 0.27528199553489685,
      "precision": 1.0,
      "recall": 0.5,
      "lead_time": 11.666666984558105
    },
    "Analog-Fidelity@5": 65.78313253012048,
    "TTE-Err@1": 24.16666603088379
  }
}