{
  "experiment_name": "r035_prefix_retrieval_atlas_raw_public_seed21",
  "dataset_dir": "data/atlas_raw_public",
  "model": {
    "type": "prefix_retrieval",
    "encoder": "transformer",
    "hidden_dim": 128,
    "embedding_dim": 128,
    "top_k": 5,
    "use_auxiliary": true,
    "use_contrastive": false,
    "use_hard_negatives": false,
    "use_utility": false
  },
  "history": [
    {
      "epoch": 1,
      "train_loss": 0.016296632544002994,
      "dev_metrics": {
        "AUPRC": 0.0025599609279322046,
        "Brier": 0.003249581401592068,
        "LeadTime@P80": 0.0,
        "LeadTimeDetail": {
          "threshold": 0.0,
          "precision": 0.0,
          "recall": 0.0,
          "lead_time": 0.0
        },
        "Analog-Fidelity@5": 98.90455531453362,
        "TTE-Err@1": 827.5
      }
    },
    {
      "epoch": 2,
      "train_loss": 0.015177176781212994,
      "dev_metrics": {
        "AUPRC": 0.0032555615843733042,
        "Brier": 0.003258262284342283,
        "LeadTime@P80": 0.0,
        "LeadTimeDetail": {
          "threshold": 0.0,
          "precision": 0.0,
          "recall": 0.0,
          "lead_time": 0.0
        },
        "Analog-Fidelity@5": 98.86117136659436,
        "TTE-Err@1": 827.5
      }
    },
    {
      "epoch": 3,
      "train_loss": 0.014578770304720037,
      "dev_metrics": {
        "AUPRC": 0.0032590983161325366,
        "Brier": 0.0033447638839043514,
        "LeadTime@P80": 0.0,
        "LeadTimeDetail": {
          "threshold": 0.0,
          "precision": 0.0,
          "recall": 0.0,
          "lead_time": 0.0
        },
        "Analog-Fidelity@5": 98.9117859725235,
        "TTE-Err@1": 827.5
      }
    },
    {
      "epoch": 4,
      "train_loss": 0.014489534702222232,
      "dev_metrics": {
        "AUPRC": 0.0032590983161325366,
        "Brier": 0.0038259346072942496,
        "LeadTime@P80": 0.0,
        "LeadTimeDetail": {
          "threshold": 0.0,
          "precision": 0.0,
          "recall": 0.0,
          "lead_time": 0.0
        },
        "Analog-Fidelity@5": 39.7939262472885,
        "TTE-Err@1": 12.5
      }
    },
    {
      "epoch": 5,
      "train_loss": 0.014183026807628993,
      "dev_metrics": {
        "AUPRC": 0.0032876712328767125,
        "Brier": 0.003244956586512383,
        "LeadTime@P80": 0.0,
        "LeadTimeDetail": {
          "threshold": 0.0,
          "precision": 0.0,
          "recall": 0.0,
          "lead_time": 0.0
        },
        "Analog-Fidelity@5": 39.830079537237886,
        "TTE-Err@1": 9.166666984558105
      }
    },
    {
      "epoch": 6,
      "train_loss": 0.015940625395235834,
      "dev_metrics": {
        "AUPRC": 0.0025624417756211033,
        "Brier": 0.003403395327828088,
        "LeadTime@P80": 0.0,
        "LeadTimeDetail": {
          "threshold": 0.0,
          "precision": 0.0,
          "recall": 0.0,
          "lead_time": 0.0
        },
        "Analog-Fidelity@5": 39.75054229934924,
        "TTE-Err@1": 22.5
      }
    },
    {
      "epoch": 7,
      "train_loss": 0.015516056227455586,
      "dev_metrics": {
        "AUPRC": 0.08219098046375752,
        "Brier": 0.003244637084724446,
        "LeadTime@P80": 0.0,
        "LeadTimeDetail": {
          "threshold": 0.0,
          "precision": 0.0,
          "recall": 0.0,
          "lead_time": 0.0
        },
        "Analog-Fidelity@5": 39.66738973246565,
        "TTE-Err@1": 837.5
      }
    },
    {
      "epoch": 8,
      "train_loss": 0.015226957097098157,
      "dev_metrics": {
        "AUPRC": 0.003264417845484222,
        "Brier": 0.0032813179553243883,
        "LeadTime@P80": 0.0,
        "LeadTimeDetail": {
          "threshold": 0.0,
          "precision": 0.0,
          "recall": 0.0,
          "lead_time": 0.0
        },
        "Analog-Fidelity@5": 79.1467823571945,
        "TTE-Err@1": 837.5
      }
    },
    {
      "epoch": 9,
      "train_loss": 0.014164536086630874,
      "dev_metrics": {
        "AUPRC": 0.08914830256104823,
        "Brier": 0.003245265852318449,
        "LeadTime@P80": 0.0,
        "LeadTimeDetail": {
          "threshold": 0.0,
          "precision": 0.0,
          "recall": 0.0,
          "lead_time": 0.0
        },
        "Analog-Fidelity@5": 19.98192335502531,
        "TTE-Err@1": 9.166666984558105
      }
    },
    {
      "epoch": 10,
      "train_loss": 0.014262317284253492,
      "dev_metrics": {
        "AUPRC": 0.0032733224222585926,
        "Brier": 0.003251487378286602,
        "LeadTime@P80": 0.0,
        "LeadTimeDetail": {
          "threshold": 0.0,
          "precision": 0.0,
          "recall": 0.0,
          "lead_time": 0.0
        },
        "Analog-Fidelity@5": 39.63485177151121,
        "TTE-Err@1": 27.5
      }
    },
    {
      "epoch": 11,
      "train_loss": 0.014132862335180088,
      "dev_metrics": {
        "AUPRC": 0.002553424233454106,
        "Brier": 0.0032481274723508446,
        "LeadTime@P80": 0.0,
        "LeadTimeDetail": {
          "threshold": 0.0,
          "precision": 0.0,
          "recall": 0.0,
          "lead_time": 0.0
        },
        "Analog-Fidelity@5": 39.580621836587135,
        "TTE-Err@1": 842.5
      }
    },
    {
      "epoch": 12,
      "train_loss": 0.013651532044287006,
      "dev_metrics": {
        "AUPRC": 0.0032876712328767125,
        "Brier": 0.003278729381508303,
        "LeadTime@P80": 0.0,
        "LeadTimeDetail": {
          "threshold": 0.0,
          "precision": 0.0,
          "recall": 0.0,
          "lead_time": 0.0
        },
        "Analog-Fidelity@5": 19.945770065075923,
        "TTE-Err@1": 9.166666984558105
      }
    }
  ],
  "best_dev_score": 0.9923769580413676,
  "dev": {
    "AUPRC": 0.0032590983161325366,
    "Brier": 0.0033447638839043514,
    "LeadTime@P80": 0.0,
    "LeadTimeDetail": {
      "threshold": 0.0,
      "precision": 0.0,
      "recall": 0.0,
      "lead_time": 0.0
    },
    "Analog-Fidelity@5": 98.9117859725235,
    "TTE-Err@1": 827.5
  },
  "test": {
    "AUPRC": 0.2738645797216655,
    "Brier": 0.005259718368014888,
    "LeadTime@P80": 5.0,
    "LeadTimeDetail": {
      "threshold": 0.35254499316215515,
      "precision": 1.0,
      "recall": 0.08333333333333333,
      "lead_time": 5.0
    },
    "Analog-Fidelity@5": 97.88297872340425,
    "TTE-Err@1": 494.1666564941406
  },
  "test_event_disjoint": {
    "AUPRC": 0.0012978979768731836,
    "Brier": 0.0015929787424888932,
    "LeadTime@P80": 0.0,
    "LeadTimeDetail": {
      "threshold": 0.0,
      "precision": 0.0,
      "recall": 0.0,
      "lead_time": 0.0
    },
    "Analog-Fidelity@5": 99.52393408318075,
    "TTE-Err@1": 827.5
  }
}