{
  "experiment_name": "r055_campaign_mem_v3_dlinear_sharp_atlasv2_public_seed7",
  "dataset_dir": "data/atlasv2_public",
  "model": {
    "type": "campaign_mem_v3",
    "forecast_encoder": "dlinear",
    "retrieval_encoder": "transformer",
    "hidden_dim": 128,
    "embedding_dim": 128,
    "top_k": 3,
    "similarity_temperature": 0.1,
    "delta_scale": 0.25,
    "use_auxiliary": true,
    "use_contrastive": true,
    "use_hard_negatives": true,
    "use_utility": false
  },
  "history": [
    {
      "epoch": 1,
      "train_loss": 0.3350287104986574,
      "dev_metrics": {
        "AUPRC": 0.7333333333333333,
        "Brier": 0.020407494636089724,
        "LeadTime@P80": 5.0,
        "LeadTimeDetail": {
          "threshold": 0.169964998960495,
          "precision": 1.0,
          "recall": 0.25,
          "lead_time": 5.0
        },
        "Analog-Fidelity@5": 76.34408602150538,
        "TTE-Err@1": 31.25
      }
    },
    {
      "epoch": 2,
      "train_loss": 0.3020213929485513,
      "dev_metrics": {
        "AUPRC": 0.756896551724138,
        "Brier": 0.015353582866157754,
        "LeadTime@P80": 10.0,
        "LeadTimeDetail": {
          "threshold": 0.2676199972629547,
          "precision": 1.0,
          "recall": 0.75,
          "lead_time": 10.0
        },
        "Analog-Fidelity@5": 77.41935483870968,
        "TTE-Err@1": 31.25
      }
    },
    {
      "epoch": 3,
      "train_loss": 0.3226723994838593,
      "dev_metrics": {
        "AUPRC": 0.7333333333333333,
        "Brier": 0.013285945468119679,
        "LeadTime@P80": 0.0,
        "LeadTimeDetail": {
          "threshold": 0.0,
          "precision": 0.0,
          "recall": 0.0,
          "lead_time": 0.0
        },
        "Analog-Fidelity@5": 76.34408602150538,
        "TTE-Err@1": 31.25
      }
    },
    {
      "epoch": 4,
      "train_loss": 0.2823707264035804,
      "dev_metrics": {
        "AUPRC": 0.6621951219512195,
        "Brier": 0.022323344077217748,
        "LeadTime@P80": 12.5,
        "LeadTimeDetail": {
          "threshold": 0.03988499939441681,
          "precision": 1.0,
          "recall": 0.5,
          "lead_time": 12.5
        },
        "Analog-Fidelity@5": 73.54838709677419,
        "TTE-Err@1": 31.25
      }
    },
    {
      "epoch": 5,
      "train_loss": 0.26962335258041886,
      "dev_metrics": {
        "AUPRC": 0.9166666666666666,
        "Brier": 0.020401392758452385,
        "LeadTime@P80": 6.666666507720947,
        "LeadTimeDetail": {
          "threshold": 0.12522800266742706,
          "precision": 1.0,
          "recall": 0.75,
          "lead_time": 6.666666507720947
        },
        "Analog-Fidelity@5": 76.98924731182795,
        "TTE-Err@1": 31.25
      }
    },
    {
      "epoch": 6,
      "train_loss": 0.26549183424205,
      "dev_metrics": {
        "AUPRC": 0.8166666666666667,
        "Brier": 0.015858206902198812,
        "LeadTime@P80": 10.0,
        "LeadTimeDetail": {
          "threshold": 0.30421799421310425,
          "precision": 1.0,
          "recall": 0.25,
          "lead_time": 10.0
        },
        "Analog-Fidelity@5": 74.19354838709677,
        "TTE-Err@1": 23.75
      }
    },
    {
      "epoch": 7,
      "train_loss": 0.26630362364799465,
      "dev_metrics": {
        "AUPRC": 0.7333333333333333,
        "Brier": 0.021290880081623095,
        "LeadTime@P80": 0.0,
        "LeadTimeDetail": {
          "threshold": 0.0,
          "precision": 0.0,
          "recall": 0.0,
          "lead_time": 0.0
        },
        "Analog-Fidelity@5": 76.98924731182795,
        "TTE-Err@1": 25.0
      }
    },
    {
      "epoch": 8,
      "train_loss": 0.26414792260078535,
      "dev_metrics": {
        "AUPRC": 0.6916666666666667,
        "Brier": 0.017680995214791804,
        "LeadTime@P80": 10.0,
        "LeadTimeDetail": {
          "threshold": 0.3160470128059387,
          "precision": 1.0,
          "recall": 0.25,
          "lead_time": 10.0
        },
        "Analog-Fidelity@5": 76.98924731182795,
        "TTE-Err@1": 25.0
      }
    },
    {
      "epoch": 9,
      "train_loss": 0.26001701976882813,
      "dev_metrics": {
        "AUPRC": 0.036967654331440794,
        "Brier": 0.025726837615444042,
        "LeadTime@P80": 0.0,
        "LeadTimeDetail": {
          "threshold": 0.0,
          "precision": 0.0,
          "recall": 0.0,
          "lead_time": 0.0
        },
        "Analog-Fidelity@5": 66.02150537634408,
        "TTE-Err@1": 31.25
      }
    },
    {
      "epoch": 10,
      "train_loss": 0.2679845087876603,
      "dev_metrics": {
        "AUPRC": 0.7333333333333333,
        "Brier": 0.02027822169210757,
        "LeadTime@P80": 10.0,
        "LeadTimeDetail": {
          "threshold": 0.12752799689769745,
          "precision": 1.0,
          "recall": 0.25,
          "lead_time": 10.0
        },
        "Analog-Fidelity@5": 78.27956989247312,
        "TTE-Err@1": 31.25
      }
    },
    {
      "epoch": 11,
      "train_loss": 0.2541403449969749,
      "dev_metrics": {
        "AUPRC": 0.8166666666666667,
        "Brier": 0.022331132929504213,
        "LeadTime@P80": 10.0,
        "LeadTimeDetail": {
          "threshold": 0.1122409999370575,
          "precision": 1.0,
          "recall": 0.25,
          "lead_time": 10.0
        },
        "Analog-Fidelity@5": 77.63440860215054,
        "TTE-Err@1": 25.0
      }
    },
    {
      "epoch": 12,
      "train_loss": 0.24584722770675677,
      "dev_metrics": {
        "AUPRC": 0.7333333333333333,
        "Brier": 0.014681811996697812,
        "LeadTime@P80": 10.0,
        "LeadTimeDetail": {
          "threshold": 0.4046359956264496,
          "precision": 1.0,
          "recall": 0.25,
          "lead_time": 10.0
        },
        "Analog-Fidelity@5": 77.20430107526882,
        "TTE-Err@1": 31.25
      }
    }
  ],
  "best_dev_score": 1.6865591397849462,
  "dev": {
    "AUPRC": 0.9166666666666666,
    "Brier": 0.020401392758452385,
    "LeadTime@P80": 6.666666507720947,
    "LeadTimeDetail": {
      "threshold": 0.12522800266742706,
      "precision": 1.0,
      "recall": 0.75,
      "lead_time": 6.666666507720947
    },
    "Analog-Fidelity@5": 76.98924731182795,
    "TTE-Err@1": 31.25
  },
  "test": {
    "AUPRC": 0.402056277056277,
    "Brier": 0.03676547067741367,
    "LeadTime@P80": 0.0,
    "LeadTimeDetail": {
      "threshold": 0.0,
      "precision": 0.0,
      "recall": 0.0,
      "lead_time": 0.0
    },
    "Analog-Fidelity@5": 68.23529411764706,
    "TTE-Err@1": 31.428571701049805
  },
  "test_event_disjoint": {
    "AUPRC": 0.7666666666666666,
    "Brier": 0.06101015034549613,
    "LeadTime@P80": 12.5,
    "LeadTimeDetail": {
      "threshold": 0.09431800246238708,
      "precision": 1.0,
      "recall": 0.6666666666666666,
      "lead_time": 12.5
    },
    "Analog-Fidelity@5": 69.07630522088354,
    "TTE-Err@1": 30.0
  }
}