{
  "experiment_name": "r158_campaign_mem_modular_no_aux_atlasv2_public_seed7",
  "dataset_dir": "data/atlasv2_public",
  "model": {
    "type": "campaign_mem_modular",
    "retrieval_encoder": "transformer",
    "hidden_dim": 128,
    "embedding_dim": 128,
    "top_k": 5,
    "similarity_temperature": 0.15,
    "delta_scale": 0.12,
    "use_auxiliary": false,
    "use_contrastive": true,
    "use_hard_negatives": true,
    "use_utility": false,
    "use_tcn_expert": true,
    "use_abstention": true,
    "use_uncertainty_gate": true,
    "uncertainty_gate_floor": 0.35,
    "selector_agreement_floor": 0.2
  },
  "history": [
    {
      "epoch": 1,
      "train_loss": 0.7330159485067951,
      "dev_metrics": {
        "AUPRC": 0.28544372294372294,
        "Brier": 0.0477401539683342,
        "LeadTime@P80": 10.0,
        "LeadTimeDetail": {
          "threshold": 0.35441699624061584,
          "precision": 1.0,
          "recall": 0.25,
          "lead_time": 10.0
        },
        "Analog-Fidelity@5": 76.77419354838709,
        "TTE-Err@1": 31.25
      },
      "proxy_event_metrics": {
        "AUPRC": 0.1394641138274415,
        "Brier": 0.13933278620243073,
        "LeadTime@P80": 0.0,
        "LeadTimeDetail": {
          "threshold": 0.0,
          "precision": 0.0,
          "recall": 0.0,
          "lead_time": 0.0
        },
        "Analog-Fidelity@5": 56.52173913043478,
        "TTE-Err@1": 27.5
      }
    },
    {
      "epoch": 2,
      "train_loss": 0.5350759790096109,
      "dev_metrics": {
        "AUPRC": 0.6947992700729927,
        "Brier": 0.015718230977654457,
        "LeadTime@P80": 7.5,
        "LeadTimeDetail": {
          "threshold": 0.3251950144767761,
          "precision": 1.0,
          "recall": 0.5,
          "lead_time": 7.5
        },
        "Analog-Fidelity@5": 80.7741935483871,
        "TTE-Err@1": 31.25
      },
      "proxy_event_metrics": {
        "AUPRC": 0.27609126984126986,
        "Brier": 0.13675054907798767,
        "LeadTime@P80": 0.0,
        "LeadTimeDetail": {
          "threshold": 0.0,
          "precision": 0.0,
          "recall": 0.0,
          "lead_time": 0.0
        },
        "Analog-Fidelity@5": 53.91304347826087,
        "TTE-Err@1": 27.5
      }
    },
    {
      "epoch": 3,
      "train_loss": 0.5329851340757658,
      "dev_metrics": {
        "AUPRC": 1.0,
        "Brier": 0.01450544036924839,
        "LeadTime@P80": 8.75,
        "LeadTimeDetail": {
          "threshold": 0.24809199571609497,
          "precision": 1.0,
          "recall": 1.0,
          "lead_time": 8.75
        },
        "Analog-Fidelity@5": 79.2258064516129,
        "TTE-Err@1": 31.25
      },
      "proxy_event_metrics": {
        "AUPRC": 0.2847494553376906,
        "Brier": 0.12916754186153412,
        "LeadTime@P80": 0.0,
        "LeadTimeDetail": {
          "threshold": 0.0,
          "precision": 0.0,
          "recall": 0.0,
          "lead_time": 0.0
        },
        "Analog-Fidelity@5": 57.826086956521735,
        "TTE-Err@1": 27.5
      }
    },
    {
      "epoch": 4,
      "train_loss": 0.4455539622263277,
      "dev_metrics": {
        "AUPRC": 0.8541666666666666,
        "Brier": 0.015561257489025593,
        "LeadTime@P80": 7.5,
        "LeadTimeDetail": {
          "threshold": 0.26504600048065186,
          "precision": 1.0,
          "recall": 0.5,
          "lead_time": 7.5
        },
        "Analog-Fidelity@5": 78.45161290322581,
        "TTE-Err@1": 31.25
      },
      "proxy_event_metrics": {
        "AUPRC": 0.24141414141414144,
        "Brier": 0.1154659315943718,
        "LeadTime@P80": 0.0,
        "LeadTimeDetail": {
          "threshold": 0.0,
          "precision": 0.0,
          "recall": 0.0,
          "lead_time": 0.0
        },
        "Analog-Fidelity@5": 56.52173913043478,
        "TTE-Err@1": 27.5
      }
    },
    {
      "epoch": 5,
      "train_loss": 0.4535079244609293,
      "dev_metrics": {
        "AUPRC": 0.95,
        "Brier": 0.018316777423024178,
        "LeadTime@P80": 8.75,
        "LeadTimeDetail": {
          "threshold": 0.21258600056171417,
          "precision": 0.8,
          "recall": 1.0,
          "lead_time": 8.75
        },
        "Analog-Fidelity@5": 71.35483870967741,
        "TTE-Err@1": 23.75
      },
      "proxy_event_metrics": {
        "AUPRC": 0.20806878306878307,
        "Brier": 0.1284707635641098,
        "LeadTime@P80": 0.0,
        "LeadTimeDetail": {
          "threshold": 0.0,
          "precision": 0.0,
          "recall": 0.0,
          "lead_time": 0.0
        },
        "Analog-Fidelity@5": 56.086956521739125,
        "TTE-Err@1": 27.5
      }
    },
    {
      "epoch": 6,
      "train_loss": 0.40136334517775063,
      "dev_metrics": {
        "AUPRC": 0.8041666666666667,
        "Brier": 0.017487209290266037,
        "LeadTime@P80": 15.0,
        "LeadTimeDetail": {
          "threshold": 0.23306800425052643,
          "precision": 1.0,
          "recall": 0.25,
          "lead_time": 15.0
        },
        "Analog-Fidelity@5": 77.80645161290323,
        "TTE-Err@1": 23.75
      },
      "proxy_event_metrics": {
        "AUPRC": 0.24006086506086508,
        "Brier": 0.12524671852588654,
        "LeadTime@P80": 0.0,
        "LeadTimeDetail": {
          "threshold": 0.0,
          "precision": 0.0,
          "recall": 0.0,
          "lead_time": 0.0
        },
        "Analog-Fidelity@5": 56.95652173913044,
        "TTE-Err@1": 27.5
      }
    },
    {
      "epoch": 7,
      "train_loss": 0.3953244714704278,
      "dev_metrics": {
        "AUPRC": 0.8041666666666667,
        "Brier": 0.01770707033574581,
        "LeadTime@P80": 15.0,
        "LeadTimeDetail": {
          "threshold": 0.2339480072259903,
          "precision": 1.0,
          "recall": 0.25,
          "lead_time": 15.0
        },
        "Analog-Fidelity@5": 79.09677419354838,
        "TTE-Err@1": 23.75
      },
      "proxy_event_metrics": {
        "AUPRC": 0.3399864024864025,
        "Brier": 0.12733468413352966,
        "LeadTime@P80": 0.0,
        "LeadTimeDetail": {
          "threshold": 0.0,
          "precision": 0.0,
          "recall": 0.0,
          "lead_time": 0.0
        },
        "Analog-Fidelity@5": 56.52173913043478,
        "TTE-Err@1": 27.5
      }
    },
    {
      "epoch": 8,
      "train_loss": 0.3712422530672866,
      "dev_metrics": {
        "AUPRC": 0.7708333333333333,
        "Brier": 0.02000008523464203,
        "LeadTime@P80": 0.0,
        "LeadTimeDetail": {
          "threshold": 0.0,
          "precision": 0.0,
          "recall": 0.0,
          "lead_time": 0.0
        },
        "Analog-Fidelity@5": 73.93548387096774,
        "TTE-Err@1": 23.75
      },
      "proxy_event_metrics": {
        "AUPRC": 0.3256854256854257,
        "Brier": 0.12207744270563126,
        "LeadTime@P80": 0.0,
        "LeadTimeDetail": {
          "threshold": 0.0,
          "precision": 0.0,
          "recall": 0.0,
          "lead_time": 0.0
        },
        "Analog-Fidelity@5": 56.086956521739125,
        "TTE-Err@1": 27.5
      }
    },
    {
      "epoch": 9,
      "train_loss": 0.4129182416010121,
      "dev_metrics": {
        "AUPRC": 0.6458333333333333,
        "Brier": 0.01942872628569603,
        "LeadTime@P80": 0.0,
        "LeadTimeDetail": {
          "threshold": 0.0,
          "precision": 0.0,
          "recall": 0.0,
          "lead_time": 0.0
        },
        "Analog-Fidelity@5": 77.80645161290323,
        "TTE-Err@1": 23.75
      },
      "proxy_event_metrics": {
        "AUPRC": 0.208511396011396,
        "Brier": 0.12313753366470337,
        "LeadTime@P80": 0.0,
        "LeadTimeDetail": {
          "threshold": 0.0,
          "precision": 0.0,
          "recall": 0.0,
          "lead_time": 0.0
        },
        "Analog-Fidelity@5": 53.47826086956522,
        "TTE-Err@1": 27.5
      }
    },
    {
      "epoch": 10,
      "train_loss": 0.4718835073518971,
      "dev_metrics": {
        "AUPRC": 0.525,
        "Brier": 0.019648229703307152,
        "LeadTime@P80": 0.0,
        "LeadTimeDetail": {
          "threshold": 0.0,
          "precision": 0.0,
          "recall": 0.0,
          "lead_time": 0.0
        },
        "Analog-Fidelity@5": 79.35483870967742,
        "TTE-Err@1": 23.75
      },
      "proxy_event_metrics": {
        "AUPRC": 0.205075979089137,
        "Brier": 0.12422072142362595,
        "LeadTime@P80": 0.0,
        "LeadTimeDetail": {
          "threshold": 0.0,
          "precision": 0.0,
          "recall": 0.0,
          "lead_time": 0.0
        },
        "Analog-Fidelity@5": 55.21739130434783,
        "TTE-Err@1": 27.5
      }
    },
    {
      "epoch": 11,
      "train_loss": 0.3637060716271945,
      "dev_metrics": {
        "AUPRC": 0.525,
        "Brier": 0.019414138048887253,
        "LeadTime@P80": 0.0,
        "LeadTimeDetail": {
          "threshold": 0.0,
          "precision": 0.0,
          "recall": 0.0,
          "lead_time": 0.0
        },
        "Analog-Fidelity@5": 79.48387096774194,
        "TTE-Err@1": 36.25
      },
      "proxy_event_metrics": {
        "AUPRC": 0.21059472934472934,
        "Brier": 0.13757246732711792,
        "LeadTime@P80": 0.0,
        "LeadTimeDetail": {
          "threshold": 0.0,
          "precision": 0.0,
          "recall": 0.0,
          "lead_time": 0.0
        },
        "Analog-Fidelity@5": 56.95652173913044,
        "TTE-Err@1": 27.5
      }
    },
    {
      "epoch": 12,
      "train_loss": 0.3243025734544345,
      "dev_metrics": {
        "AUPRC": 0.7333333333333333,
        "Brier": 0.019787335768342018,
        "LeadTime@P80": 10.0,
        "LeadTimeDetail": {
          "threshold": 0.18443000316619873,
          "precision": 1.0,
          "recall": 0.25,
          "lead_time": 10.0
        },
        "Analog-Fidelity@5": 74.83870967741936,
        "TTE-Err@1": 31.25
      },
      "proxy_event_metrics": {
        "AUPRC": 0.2432659932659933,
        "Brier": 0.12629170715808868,
        "LeadTime@P80": 0.0,
        "LeadTimeDetail": {
          "threshold": 0.0,
          "precision": 0.0,
          "recall": 0.0,
          "lead_time": 0.0
        },
        "Analog-Fidelity@5": 58.26086956521739,
        "TTE-Err@1": 27.5
      }
    },
    {
      "epoch": 13,
      "train_loss": 0.339962250293662,
      "dev_metrics": {
        "AUPRC": 0.7333333333333333,
        "Brier": 0.01966669037938118,
        "LeadTime@P80": 10.0,
        "LeadTimeDetail": {
          "threshold": 0.1923770010471344,
          "precision": 1.0,
          "recall": 0.25,
          "lead_time": 10.0
        },
        "Analog-Fidelity@5": 74.19354838709677,
        "TTE-Err@1": 31.25
      },
      "proxy_event_metrics": {
        "AUPRC": 0.24006086506086508,
        "Brier": 0.12082147598266602,
        "LeadTime@P80": 0.0,
        "LeadTimeDetail": {
          "threshold": 0.0,
          "precision": 0.0,
          "recall": 0.0,
          "lead_time": 0.0
        },
        "Analog-Fidelity@5": 58.26086956521739,
        "TTE-Err@1": 27.5
      }
    },
    {
      "epoch": 14,
      "train_loss": 0.33673901617799173,
      "dev_metrics": {
        "AUPRC": 0.5428571428571428,
        "Brier": 0.019564909860491753,
        "LeadTime@P80": 0.0,
        "LeadTimeDetail": {
          "threshold": 0.0,
          "precision": 0.0,
          "recall": 0.0,
          "lead_time": 0.0
        },
        "Analog-Fidelity@5": 74.06451612903226,
        "TTE-Err@1": 31.25
      },
      "proxy_event_metrics": {
        "AUPRC": 0.20646441372247823,
        "Brier": 0.1264781802892685,
        "LeadTime@P80": 0.0,
        "LeadTimeDetail": {
          "threshold": 0.0,
          "precision": 0.0,
          "recall": 0.0,
          "lead_time": 0.0
        },
        "Analog-Fidelity@5": 57.826086956521735,
        "TTE-Err@1": 27.5
      }
    },
    {
      "epoch": 15,
      "train_loss": 0.30793799439521685,
      "dev_metrics": {
        "AUPRC": 0.5428571428571428,
        "Brier": 0.019521944224834442,
        "LeadTime@P80": 0.0,
        "LeadTimeDetail": {
          "threshold": 0.0,
          "precision": 0.0,
          "recall": 0.0,
          "lead_time": 0.0
        },
        "Analog-Fidelity@5": 79.74193548387096,
        "TTE-Err@1": 25.0
      },
      "proxy_event_metrics": {
        "AUPRC": 0.2373136123136123,
        "Brier": 0.1221611499786377,
        "LeadTime@P80": 0.0,
        "LeadTimeDetail": {
          "threshold": 0.0,
          "precision": 0.0,
          "recall": 0.0,
          "lead_time": 0.0
        },
        "Analog-Fidelity@5": 56.95652173913044,
        "TTE-Err@1": 27.5
      }
    },
    {
      "epoch": 16,
      "train_loss": 0.3249696947668241,
      "dev_metrics": {
        "AUPRC": 0.5178571428571428,
        "Brier": 0.019481822848320007,
        "LeadTime@P80": 0.0,
        "LeadTimeDetail": {
          "threshold": 0.0,
          "precision": 0.0,
          "recall": 0.0,
          "lead_time": 0.0
        },
        "Analog-Fidelity@5": 78.19354838709678,
        "TTE-Err@1": 26.25
      },
      "proxy_event_metrics": {
        "AUPRC": 0.27266252266252267,
        "Brier": 0.12219031900167465,
        "LeadTime@P80": 0.0,
        "LeadTimeDetail": {
          "threshold": 0.0,
          "precision": 0.0,
          "recall": 0.0,
          "lead_time": 0.0
        },
        "Analog-Fidelity@5": 59.56521739130435,
        "TTE-Err@1": 27.5
      }
    },
    {
      "epoch": 17,
      "train_loss": 0.3011546579261893,
      "dev_metrics": {
        "AUPRC": 0.5178571428571428,
        "Brier": 0.01956479623913765,
        "LeadTime@P80": 0.0,
        "LeadTimeDetail": {
          "threshold": 0.0,
          "precision": 0.0,
          "recall": 0.0,
          "lead_time": 0.0
        },
        "Analog-Fidelity@5": 78.83870967741935,
        "TTE-Err@1": 26.25
      },
      "proxy_event_metrics": {
        "AUPRC": 0.23710317460317462,
        "Brier": 0.12431080639362335,
        "LeadTime@P80": 0.0,
        "LeadTimeDetail": {
          "threshold": 0.0,
          "precision": 0.0,
          "recall": 0.0,
          "lead_time": 0.0
        },
        "Analog-Fidelity@5": 59.130434782608695,
        "TTE-Err@1": 27.5
      }
    },
    {
      "epoch": 18,
      "train_loss": 0.32622257011121814,
      "dev_metrics": {
        "AUPRC": 0.6428571428571428,
        "Brier": 0.019544657319784164,
        "LeadTime@P80": 10.0,
        "LeadTimeDetail": {
          "threshold": 0.21573400497436523,
          "precision": 1.0,
          "recall": 0.25,
          "lead_time": 10.0
        },
        "Analog-Fidelity@5": 78.45161290322581,
        "TTE-Err@1": 26.25
      },
      "proxy_event_metrics": {
        "AUPRC": 0.2834249084249084,
        "Brier": 0.1174226626753807,
        "LeadTime@P80": 0.0,
        "LeadTimeDetail": {
          "threshold": 0.0,
          "precision": 0.0,
          "recall": 0.0,
          "lead_time": 0.0
        },
        "Analog-Fidelity@5": 60.43478260869565,
        "TTE-Err@1": 27.5
      }
    },
    {
      "epoch": 19,
      "train_loss": 0.3145688173433417,
      "dev_metrics": {
        "AUPRC": 0.6428571428571428,
        "Brier": 0.019478557631373405,
        "LeadTime@P80": 10.0,
        "LeadTimeDetail": {
          "threshold": 0.21978400647640228,
          "precision": 1.0,
          "recall": 0.25,
          "lead_time": 10.0
        },
        "Analog-Fidelity@5": 79.74193548387096,
        "TTE-Err@1": 31.25
      },
      "proxy_event_metrics": {
        "AUPRC": 0.23424075924075924,
        "Brier": 0.13041067123413086,
        "LeadTime@P80": 0.0,
        "LeadTimeDetail": {
          "threshold": 0.0,
          "precision": 0.0,
          "recall": 0.0,
          "lead_time": 0.0
        },
        "Analog-Fidelity@5": 59.56521739130435,
        "TTE-Err@1": 27.5
      }
    },
    {
      "epoch": 20,
      "train_loss": 0.2849748609545024,
      "dev_metrics": {
        "AUPRC": 0.6428571428571428,
        "Brier": 0.01914854161441326,
        "LeadTime@P80": 0.0,
        "LeadTimeDetail": {
          "threshold": 0.0,
          "precision": 0.0,
          "recall": 0.0,
          "lead_time": 0.0
        },
        "Analog-Fidelity@5": 80.38709677419355,
        "TTE-Err@1": 31.25
      },
      "proxy_event_metrics": {
        "AUPRC": 0.2573934837092732,
        "Brier": 0.1286751925945282,
        "LeadTime@P80": 0.0,
        "LeadTimeDetail": {
          "threshold": 0.0,
          "precision": 0.0,
          "recall": 0.0,
          "lead_time": 0.0
        },
        "Analog-Fidelity@5": 60.43478260869565,
        "TTE-Err@1": 27.5
      }
    }
  ],
  "best_dev_score": 1.3151035759792462,
  "checkpoint_average_top_k": 5,
  "dev": {
    "AUPRC": 0.95,
    "Brier": 0.018793845549225807,
    "LeadTime@P80": 8.75,
    "LeadTimeDetail": {
      "threshold": 0.19886699318885803,
      "precision": 0.8,
      "recall": 1.0,
      "lead_time": 8.75
    },
    "Analog-Fidelity@5": 72.51612903225806,
    "TTE-Err@1": 23.75
  },
  "test": {
    "AUPRC": 0.6337662337662338,
    "Brier": 0.032116517424583435,
    "LeadTime@P80": 5.0,
    "LeadTimeDetail": {
      "threshold": 0.3113049864768982,
      "precision": 1.0,
      "recall": 0.14285714285714285,
      "lead_time": 5.0
    },
    "Analog-Fidelity@5": 71.29411764705881,
    "TTE-Err@1": 28.571428298950195
  },
  "test_event_disjoint": {
    "AUPRC": 0.5439393939393938,
    "Brier": 0.05715680494904518,
    "LeadTime@P80": 17.5,
    "LeadTimeDetail": {
      "threshold": 0.2314469963312149,
      "precision": 1.0,
      "recall": 0.3333333333333333,
      "lead_time": 17.5
    },
    "Analog-Fidelity@5": 72.77108433734941,
    "TTE-Err@1": 30.0
  }
}